{
  "project_info": {
    "project_number": "380130451057",
    "firebase_url": "https://mary-matha-college.firebaseio.com",
    "project_id": "mary-matha-college",
    "storage_bucket": "mary-matha-college.appspot.com"
  },
  "client": [
    {
      "client_info": {
        "mobilesdk_app_id": "1:380130451057:android:bd6892a09d672aa7f305d0",
        "android_client_info": {
          "package_name": "com.example.marymathacollege"
        }
      },
      "oauth_client": [
        {
          "client_id": "380130451057-r5b98v1qr772rdsvom005uh9qr6lchui.apps.googleusercontent.com",
          "client_type": 3
        }
      ],
      "api_key": [
        {
          "current_key": "AIzaSyDUlIqZNriQiTTsPBB6BlXjoaRxDTf2jsQ"
        }
      ],
      "services": {
        "appinvite_service": {
          "other_platform_oauth_client": [
            {
              "client_id": "380130451057-r5b98v1qr772rdsvom005uh9qr6lchui.apps.googleusercontent.com",
              "client_type": 3
            }
          ]
        }
      }
    },
    {
      "client_info": {
        "mobilesdk_app_id": "1:380130451057:android:4385b2cc1d7f0762f305d0",
        "android_client_info": {
          "package_name": "com.example.marymathauser"
        }
      },
      "oauth_client": [
        {
          "client_id": "380130451057-r5b98v1qr772rdsvom005uh9qr6lchui.apps.googleusercontent.com",
          "client_type": 3
        }
      ],
      "api_key": [
        {
          "current_key": "AIzaSyDUlIqZNriQiTTsPBB6BlXjoaRxDTf2jsQ"
        }
      ],
      "services": {
        "appinvite_service": {
          "other_platform_oauth_client": [
            {
              "client_id": "380130451057-r5b98v1qr772rdsvom005uh9qr6lchui.apps.googleusercontent.com",
              "client_type": 3
            }
          ]
        }
      }
    }
  ],
  "configuration_version": "1"
}